PTJPLSM/ECOv002-cal-val-PT-JPL-SM-inputs.csv
PTJPLSM/ECOv002-cal-val-PT-JPL-SM-outputs.csv
PTJPLSM/ECOv002-static-tower-PT-JPL-SM-inputs.csv
PTJPLSM/ECOv002_calval_PTJPLSM_inputs.py
PTJPLSM/ECOv002_static_tower_PTJPLSM_inputs.py
PTJPLSM/PTJPLSM.py
PTJPLSM/__init__.py
PTJPLSM/constants.py
PTJPLSM/exceptions.py
PTJPLSM/generate_PTJPLSM_raster_inputs.py
PTJPLSM/generate_PTJPLSM_table_inputs.py
PTJPLSM/model.py
PTJPLSM/process_PTJPLSM_table.py
PTJPLSM/verify.py
PTJPLSM/version.py
PTJPLSM/partitioning/__init__.py
PTJPLSM/partitioning/canopy_latent_heat_flux.py
PTJPLSM/partitioning/fREW.py
PTJPLSM/partitioning/fTRM.py
PTJPLSM/partitioning/partitioning.py
PTJPLSM/partitioning/soil_latent_heat_flux.py
ptjplsm-1.10.0.dist-info/licenses/LICENSE
tests/__init__.py
tests/test_import_PTJPLSM.py
tests/test_import_dependencies.py
tests/test_verify.py
ptjplsm-1.10.0.dist-info/METADATA
ptjplsm-1.10.0.dist-info/WHEEL
ptjplsm-1.10.0.dist-info/top_level.txt
ptjplsm-1.10.0.dist-info/RECORD
