Metadata-Version: 2.4
Name: PTJPLSM
Version: 1.10.0
Summary: Priestley-Taylor Jet Propulsion Laboratory Soil Moisture Evapotranspiration Model
Author-email: Gregory Halverson <gregory.h.halverson@jpl.nasa.gov>, "Joshua B. Fisher" <jbfisher@chapman.edu>, "Claire S. Villanueva-Weeks" <claire.s.villanueva-weeks@jpl.gov>
Project-URL: Homepage, https://github.com/JPL-Evapotranspiration-Algorithms/PTJPLSM
Classifier: Programming Language :: Python :: 3
Classifier: Operating System :: OS Independent
Requires-Python: >=3.10
License-File: LICENSE
Requires-Dist: carlson-leaf-area-index
Requires-Dist: check-distribution>=1.1.0
Requires-Dist: daylight-evapotranspiration
Requires-Dist: ECOv002-calval-tables>=1.7.1
Requires-Dist: ECOv002-CMR>=1.0.5
Requires-Dist: ECOv002-granules>=1.0.3
Requires-Dist: ECOv003-granules
Requires-Dist: gedi-canopy-height
Requires-Dist: GEOS5FP>=1.1.1
Requires-Dist: monte-carlo-sensitivity>=1.4.0
Requires-Dist: numpy
Requires-Dist: pandas
Requires-Dist: PTJPL>=1.8.1
Requires-Dist: pytictoc
Requires-Dist: rasters>=1.9.0
Requires-Dist: scikit-learn
Requires-Dist: seaborn
Requires-Dist: SEBAL-soil-heat-flux
Requires-Dist: soil-capacity-wilting>=1.2.0
Requires-Dist: solar-apparent-time>=1.5.3
Requires-Dist: sun-angles>=1.6.0
Requires-Dist: verma-net-radiation>=1.7.0
Provides-Extra: dev
Requires-Dist: build; extra == "dev"
Requires-Dist: pytest>=6.0; extra == "dev"
Requires-Dist: pytest-cov; extra == "dev"
Requires-Dist: jupyter; extra == "dev"
Requires-Dist: pytest; extra == "dev"
Requires-Dist: twine; extra == "dev"
Dynamic: license-file
